cloudselect/__init__.py
cloudselect/defaults.py
cloudselect/logger.py
cloudselect/settings.yml
cloudselect/version.py
cloudselect/client/__init__.py
cloudselect/client/cache.py
cloudselect/client/config.py
cloudselect/client/dbshell.py
cloudselect/client/instance.py
cloudselect/client/shell.py
cloudselect/cloud/__init__.py
cloudselect/cloud/base.py
cloudselect/cloud/aws/__init__.py
cloudselect/cloud/aws/client.py
cloudselect/cloud/aws/instance.py
cloudselect/cloud/aws/prices.py
cloudselect/cloud/google/__init__.py
cloudselect/cloud/google/client.py
cloudselect/cloud/google/instance.py
cloudselect/cloud/google/prices.py
cloudselect/main/__init__.py
cloudselect/main/cache.py
cloudselect/main/client.py
cloudselect/main/colors.py
cloudselect/main/oras.py
cloudselect/main/schemas.py
cloudselect/main/selectors.py
cloudselect/main/settings.py
cloudselect/main/table.py
cloudselect/main/solve/__init__.py
cloudselect/main/solve/database.py
cloudselect/main/solve/properties.py
cloudselect/main/solve/solver.py
cloudselect/tests/__init__.py
cloudselect/tests/helpers.py
cloudselect/tests/test_instance.py
cloudselect/tests/test_selector.py
cloudselect/tests/test_settings.py
cloudselect/tests/test_utils.py
cloudselect/utils/__init__.py
cloudselect/utils/fileio.py
cloudselect/utils/misc.py
cloudselect/utils/terminal.py
cloud_select_tool-0.1.0.dist-info/LICENSE
cloud_select_tool-0.1.0.dist-info/METADATA
cloud_select_tool-0.1.0.dist-info/NOTICE
cloud_select_tool-0.1.0.dist-info/WHEEL
cloud_select_tool-0.1.0.dist-info/entry_points.txt
cloud_select_tool-0.1.0.dist-info/top_level.txt
cloud_select_tool-0.1.0.dist-info/RECORD
