Metadata-Version: 2.1
Name: cloud-select-tool
Version: 0.1.0
Summary: Tool for calculating costs and needs between cloud and HPC.
Home-page: https://github.com/converged-computing/cloud-select
Author: Vanessa Sochat
Author-email: vsoch@users.noreply.github.com
Maintainer: Vanessa Sochat
License: LICENSE
Keywords: cloud,cost,hpc
Classifier: Intended Audience :: Science/Research
Classifier: Intended Audience :: Developers
Classifier: License :: OSI Approved :: MIT License
Classifier: Programming Language :: Python
Classifier: Topic :: Software Development
Classifier: Topic :: Scientific/Engineering
Classifier: Operating System :: Unix
Classifier: Programming Language :: Python :: 3.8
License-File: LICENSE
License-File: NOTICE
Requires-Dist: ruamel.yaml
Requires-Dist: jsonschema
Requires-Dist: rich
Requires-Dist: oras >=0.2.25
Requires-Dist: requests
Requires-Dist: pick
Provides-Extra: all
Requires-Dist: ruamel.yaml ; extra == 'all'
Requires-Dist: jsonschema ; extra == 'all'
Requires-Dist: rich ; extra == 'all'
Requires-Dist: oras >=0.2.25 ; extra == 'all'
Requires-Dist: requests ; extra == 'all'
Requires-Dist: pick ; extra == 'all'
Requires-Dist: google-auth ; extra == 'all'
Requires-Dist: google-api-python-client ; extra == 'all'
Requires-Dist: boto3 ; extra == 'all'
Requires-Dist: pytest >=4.6.2 ; extra == 'all'
Provides-Extra: aws
Requires-Dist: boto3 ; extra == 'aws'
Provides-Extra: google
Requires-Dist: google-auth ; extra == 'google'
Requires-Dist: google-api-python-client ; extra == 'google'
